README.rst
setup.py
aex_accounts/__init__.py
aex_accounts/account.py
aex_accounts/version.py
aex_accounts/models/__init__.py
aex_accounts/models/collection.py
aex_accounts/models/name_availability.py
aex_accounts/models/region_details.py
aex_accounts/models/regions.py
continuous_delivery/__init__.py
continuous_delivery/continuous_delivery.py
continuous_delivery/credentials.py
continuous_delivery/exceptions.py
continuous_delivery/version.py
continuous_delivery/models/__init__.py
continuous_delivery/models/authorization_info.py
continuous_delivery/models/authorization_info_parameters.py
continuous_delivery/models/build_configuration.py
continuous_delivery/models/ci_artifact.py
continuous_delivery/models/ci_configuration.py
continuous_delivery/models/ci_result.py
continuous_delivery/models/create_options.py
continuous_delivery/models/provisioning_configuration.py
continuous_delivery/models/provisioning_configuration_source.py
continuous_delivery/models/provisioning_configuration_target.py
continuous_delivery/models/slot_swap_configuration.py
continuous_delivery/models/source_repository.py
vsts_cd_manager/__init__.py
vsts_cd_manager/continuous_delivery_manager.py
vsts_cd_manager.egg-info/PKG-INFO
vsts_cd_manager.egg-info/SOURCES.txt
vsts_cd_manager.egg-info/dependency_links.txt
vsts_cd_manager.egg-info/requires.txt
vsts_cd_manager.egg-info/top_level.txt
vsts_info_provider/__init__.py
vsts_info_provider/exceptions.py
vsts_info_provider/version.py
vsts_info_provider/vsts_info_provider.py
vsts_info_provider/models/__init__.py
vsts_info_provider/models/collection_info.py
vsts_info_provider/models/repository_info.py
vsts_info_provider/models/team_project_info.py
vsts_info_provider/models/vsts_info.py