Metadata-Version: 1.0
Name: vsts-cd-manager
Version: 1.0.1
Summary: Python wrapper around some of the VSTS APIs
Home-page: https://github.com/microsoft/vsts-cd-manager
Author: UNKNOWN
Author-email: jpricket@microsoft.com
License: UNKNOWN
Keywords: Microsoft,VSTS,Team Services,SDK,AzureTfs
Platform: UNKNOWN
